{
    "language": "java",
    "ground_truth": {
        "./Compiler.java": [],
        "./frontend/Lexer.java": [],
        "./frontend/Node.java": [],
        "./frontend/Parser.java": [
            22,
            26,
            233,
            316,
            317,
            335,
            336,
            367,
            382,
            383,
            383,
            385,
            386,
            475,
            476,
            476
        ],
        "./frontend/Token.java": [],
        "./frontend/TokenType.java": [],
        "./frontend/Type.java": []
    }
}