{
  "case": "9\\1601",
  "source_type": "selected_reference_fallback",
  "selected_reference_file": "D:\\vscode\\ruance\\FLAME\\data\\data_structures\\debugta_selected_reference\\9\\1601\\selected_reference.c",
  "aligned_reference_file": "D:\\vscode\\ruance\\FLAME\\data\\data_structures\\debugta_aligned_reference\\9\\1601\\aligned_reference.c",
  "effective_reference_file": "D:\\vscode\\ruance\\FLAME\\data\\data_structures\\debugta_effective_reference\\9\\1601\\effective_reference.c",
  "selected_reference_compile_ok": true,
  "aligned_reference_compile_ok": false,
  "aligned_may_be_broken": true,
  "selected_compile_error": "",
  "aligned_compile_error": "D:\\vscode\\ruance\\FLAME\\data\\data_structures\\debugta_aligned_reference\\9\\1601\\aligned_reference.c: In function 'main':\nD:\\vscode\\ruance\\FLAME\\data\\data_structures\\debugta_aligned_reference\\9\\1601\\aligned_reference.c:8:30: error: redeclaration of 'b' with no linkage\n     int a[100],b[100],c[100],b[100],x1,y1,num;\n                              ^\nD:\\vscode\\ruance\\FLAME\\data\\data_structures\\debugta_aligned_reference\\9\\1601\\aligned_reference.c:8:16: note: previous declaration of 'b' was here\n     int a[100],b[100],c[100],b[100],x1,y1,num;\n                ^\nD:\\vscode\\ruance\\FLAME\\data\\data_structures\\debugta_aligned_reference\\9\\1601\\aligned_reference.c:9:9: error: redeclaration of 'c' with no linkage\n     int c[100];\n         ^\nD:\\vscode\\ruance\\FLAME\\data\\data_structures\\debugta_aligned_reference\\9\\1601\\aligned_reference.c:8:23: note: previous declaration of 'c' was here\n     int a[100],b[100],c[100],b[100],x1,y1,num;\n                       ^\n"
}