{
    "Compiler.java": {
        "start": 0,
        "end": 43
    },
    "fault/Fault.java": {
        "start": 44,
        "end": 251
    },
    "fault/FaultInfo.java": {
        "start": 252,
        "end": 285
    },
    "front/lexer/Lexer.java": {
        "start": 286,
        "end": 982
    },
    "front/lexer/Token.java": {
        "start": 983,
        "end": 1042
    },
    "front/lexer/TokenType.java": {
        "start": 1043,
        "end": 1477
    },
    "front/parser/Parser.java": {
        "start": 1478,
        "end": 1873
    },
    "front/parser/V.java": {
        "start": 1874,
        "end": 1958
    },
    "front/parser/Vn.java": {
        "start": 1959,
        "end": 2003
    },
    "front/parser/VnType.java": {
        "start": 2004,
        "end": 2181
    },
    "middle/optimiser/Optimizer.java": {
        "start": 2182,
        "end": 2185
    },
    "middle/symbol/Symbol.java": {
        "start": 2186,
        "end": 2250
    },
    "middle/visitor/Visitor.java": {
        "start": 2251,
        "end": 2254
    }
}