{
    "Compiler.java": {
        "start": 0,
        "end": 39
    },
    "Lexer.java": {
        "start": 40,
        "end": 107
    },
    "LineSplitter.java": {
        "start": 108,
        "end": 390
    },
    "Token.java": {
        "start": 391,
        "end": 480
    },
    "error_part/Debug.java": {
        "start": 481,
        "end": 489
    },
    "error_part/Error.java": {
        "start": 490,
        "end": 538
    },
    "error_part/ErrorList.java": {
        "start": 539,
        "end": 562
    }
}