{
  "case": "0\\2271",
  "source_type": "selected_reference_fallback",
  "selected_reference_file": "D:\\vscode\\ruance\\FLAME\\data\\data_structures\\debugta_selected_reference\\0\\2271\\selected_reference.c",
  "aligned_reference_file": "D:\\vscode\\ruance\\FLAME\\data\\data_structures\\debugta_aligned_reference\\0\\2271\\aligned_reference.c",
  "effective_reference_file": "D:\\vscode\\ruance\\FLAME\\data\\data_structures\\debugta_effective_reference\\0\\2271\\effective_reference.c",
  "selected_reference_compile_ok": true,
  "aligned_reference_compile_ok": false,
  "aligned_may_be_broken": true,
  "selected_compile_error": "",
  "aligned_compile_error": "D:\\vscode\\ruance\\FLAME\\data\\data_structures\\debugta_aligned_reference\\0\\2271\\aligned_reference.c:4:29: error: redefinition of parameter 'c'\n void sert(int i, int c, int c, int k)\n                             ^\nD:\\vscode\\ruance\\FLAME\\data\\data_structures\\debugta_aligned_reference\\0\\2271\\aligned_reference.c:4:22: note: previous definition of 'c' was here\n void sert(int i, int c, int c, int k)\n                      ^\nD:\\vscode\\ruance\\FLAME\\data\\data_structures\\debugta_aligned_reference\\0\\2271\\aligned_reference.c: In function 'main':\nD:\\vscode\\ruance\\FLAME\\data\\data_structures\\debugta_aligned_reference\\0\\2271\\aligned_reference.c:19:18: error: redeclaration of 'c' with no linkage\n     int  i = 0,c,c,k = 0,k,l,n;\n                  ^\nD:\\vscode\\ruance\\FLAME\\data\\data_structures\\debugta_aligned_reference\\0\\2271\\aligned_reference.c:19:16: note: previous declaration of 'c' was here\n     int  i = 0,c,c,k = 0,k,l,n;\n                ^\nD:\\vscode\\ruance\\FLAME\\data\\data_structures\\debugta_aligned_reference\\0\\2271\\aligned_reference.c:19:26: error: redeclaration of 'k' with no linkage\n     int  i = 0,c,c,k = 0,k,l,n;\n                          ^\nD:\\vscode\\ruance\\FLAME\\data\\data_structures\\debugta_aligned_reference\\0\\2271\\aligned_reference.c:19:20: note: previous definition of 'k' was here\n     int  i = 0,c,c,k = 0,k,l,n;\n                    ^\nD:\\vscode\\ruance\\FLAME\\data\\data_structures\\debugta_aligned_reference\\0\\2271\\aligned_reference.c:20:21: error: redeclaration of 'i' with no linkage\n     int e, f, g, h, i, j;\n                     ^\nD:\\vscode\\ruance\\FLAME\\data\\data_structures\\debugta_aligned_reference\\0\\2271\\aligned_reference.c:19:10: note: previous definition of 'i' was here\n     int  i = 0,c,c,k = 0,k,l,n;\n          ^\n"
}