{
    "language": "java",
    "ground_truth": {
        "./Compiler.java": [
            9,
            10
        ],
        "./Error/error.java": [
            20,
            21
        ],
        "./Node/AddExpNode.java": [],
        "./Node/BTypeNode.java": [],
        "./Node/BlockItemNode.java": [],
        "./Node/BlockNode.java": [],
        "./Node/CharacterNode.java": [],
        "./Node/CompUnitNode.java": [],
        "./Node/CondNode.java": [],
        "./Node/ConstDeclNode.java": [],
        "./Node/ConstDefNode.java": [],
        "./Node/ConstExpNode.java": [],
        "./Node/ConstInitValNode.java": [],
        "./Node/DeclNode.java": [],
        "./Node/EqExpNode.java": [],
        "./Node/ExpNode.java": [],
        "./Node/ForStmtNode.java": [],
        "./Node/FuncDefNode.java": [],
        "./Node/FuncFParamNode.java": [],
        "./Node/FuncFParamsNode.java": [],
        "./Node/FuncRParamsNode.java": [],
        "./Node/FuncTypeNode.java": [],
        "./Node/InitValNode.java": [],
        "./Node/LAndExpNode.java": [],
        "./Node/LOrExpNode.java": [],
        "./Node/LValNode.java": [],
        "./Node/MainFuncDefNode.java": [],
        "./Node/MulExpNode.java": [],
        "./Node/NodeType.java": [],
        "./Node/NumberNode.java": [],
        "./Node/PrimaryExpNode.java": [],
        "./Node/RelExpNode.java": [],
        "./Node/StmtNode.java": [],
        "./Node/UnaryExpNode.java": [],
        "./Node/UnaryOpNode.java": [],
        "./Node/VarDeclNode.java": [],
        "./Node/VarDefNode.java": [],
        "./Token/Token.java": [],
        "./Token/TokenType.java": [],
        "./frontend/Lexer.java": [
            45,
            46
        ],
        "./frontend/Parser.java": [
            3,
            4,
            6,
            7,
            7,
            8,
            9,
            21,
            22,
            26,
            27,
            73,
            74,
            74,
            80,
            81,
            81,
            87,
            91,
            92,
            104,
            107,
            111,
            112,
            350,
            531,
            584,
            723,
            973,
            974,
            982,
            983
        ]
    }
}