{
    "Compiler.java": {
        "start": 0,
        "end": 12
    },
    "frontend/AddExp.java": {
        "start": 13,
        "end": 67
    },
    "frontend/Block.java": {
        "start": 68,
        "end": 143
    },
    "frontend/CompUnit.java": {
        "start": 144,
        "end": 224
    },
    "frontend/Cond.java": {
        "start": 225,
        "end": 249
    },
    "frontend/ConstDecl.java": {
        "start": 250,
        "end": 327
    },
    "frontend/ConstDef.java": {
        "start": 328,
        "end": 410
    },
    "frontend/ConstExp.java": {
        "start": 411,
        "end": 441
    },
    "frontend/ConstInitVal.java": {
        "start": 442,
        "end": 519
    },
    "frontend/EqExp.java": {
        "start": 520,
        "end": 570
    },
    "frontend/ErrorType.java": {
        "start": 571,
        "end": 589
    },
    "frontend/Exp.java": {
        "start": 590,
        "end": 626
    },
    "frontend/ForStmt.java": {
        "start": 627,
        "end": 677
    },
    "frontend/FuncDef.java": {
        "start": 678,
        "end": 768
    },
    "frontend/FuncFParam.java": {
        "start": 769,
        "end": 822
    },
    "frontend/FuncFParams.java": {
        "start": 823,
        "end": 875
    },
    "frontend/FuncRParams.java": {
        "start": 876,
        "end": 928
    },
    "frontend/FuncType.java": {
        "start": 929,
        "end": 965
    },
    "frontend/GetChar.java": {
        "start": 966,
        "end": 1032
    },
    "frontend/GiveTokener.java": {
        "start": 1033,
        "end": 1100
    },
    "frontend/InitVal.java": {
        "start": 1101,
        "end": 1182
    },
    "frontend/LOrExp.java": {
        "start": 1183,
        "end": 1234
    },
    "frontend/LVal.java": {
        "start": 1235,
        "end": 1292
    },
    "frontend/LandExp.java": {
        "start": 1293,
        "end": 1345
    },
    "frontend/Lexer.java": {
        "start": 1346,
        "end": 1647
    },
    "frontend/MainFuncDef.java": {
        "start": 1648,
        "end": 1716
    },
    "frontend/MulExp.java": {
        "start": 1717,
        "end": 1766
    },
    "frontend/MyCharacter.java": {
        "start": 1767,
        "end": 1793
    },
    "frontend/Node.java": {
        "start": 1794,
        "end": 1799
    },
    "frontend/Number.java": {
        "start": 1800,
        "end": 1827
    },
    "frontend/Parser.java": {
        "start": 1828,
        "end": 1851
    },
    "frontend/PrimaryExp.java": {
        "start": 1852,
        "end": 1931
    },
    "frontend/RelExp.java": {
        "start": 1932,
        "end": 1983
    },
    "frontend/Stmt.java": {
        "start": 1984,
        "end": 2065
    },
    "frontend/StmtAssign.java": {
        "start": 2066,
        "end": 2162
    },
    "frontend/StmtBlock.java": {
        "start": 2163,
        "end": 2192
    },
    "frontend/StmtBreak.java": {
        "start": 2193,
        "end": 2230
    },
    "frontend/StmtContinue.java": {
        "start": 2231,
        "end": 2268
    },
    "frontend/StmtExp.java": {
        "start": 2269,
        "end": 2315
    },
    "frontend/StmtFor.java": {
        "start": 2316,
        "end": 2432
    },
    "frontend/StmtIf.java": {
        "start": 2433,
        "end": 2518
    },
    "frontend/StmtPrintf.java": {
        "start": 2519,
        "end": 2604
    },
    "frontend/StmtReturn.java": {
        "start": 2605,
        "end": 2653
    },
    "frontend/Token.java": {
        "start": 2654,
        "end": 2689
    },
    "frontend/TokenType.java": {
        "start": 2690,
        "end": 2745
    },
    "frontend/UnaryExp.java": {
        "start": 2746,
        "end": 2849
    },
    "frontend/UnaryOp.java": {
        "start": 2850,
        "end": 2884
    },
    "frontend/VarDecl.java": {
        "start": 2885,
        "end": 2948
    },
    "frontend/VarDef.java": {
        "start": 2949,
        "end": 3030
    },
    "frontend/WriteIntoF.java": {
        "start": 3031,
        "end": 3060
    }
}